opencrypt/__init__.py
opencrypt/__main__.py
opencrypt/_crypto.py
opencrypt-0.5.1.dist-info/LICENSE
opencrypt-0.5.1.dist-info/METADATA
opencrypt-0.5.1.dist-info/WHEEL
opencrypt-0.5.1.dist-info/entry_points.txt
opencrypt-0.5.1.dist-info/top_level.txt
opencrypt-0.5.1.dist-info/RECORD
