Metadata-Version: 2.1
Name: opencrypt
Version: 0.5.1
Summary: Symmetric encryption and decryption compatible with openSSL.
Home-page: https://github.com/EbryxLabs/opencrypt
Author: Rana Awais
Author-email: rana.awais@ebryx.com
License: UNKNOWN
Platform: UNKNOWN
Classifier: Programming Language :: Python :: 3
Classifier: License :: OSI Approved :: MIT License
Classifier: Operating System :: OS Independent
Requires-Dist: cryptography
